32_bit_divider.v
`timescale 1ns/100ps
//module of 32 bit divider
module bit32_divider (dividend,divider,s,quotient,remainder,error);

input [31:0] dividend;
input [31:0] divider;
input s;//switch between unsigned(s == 0) and signed(s == 1) division mode
output [31:0] quotient;
output [31:0] remainder;
output error;//error sign, report error when divider == 0

reg [31:0] quotient;
reg [31:0] remainder;
reg error;
reg [31:0] tdividend;//temporarily save dividend
reg [31:0] tdivider;//temporarily save divider
reg [4:0] L1; //MSB of dividend
reg [4:0] L2; //MSB of divider
reg [4:0] d;  //difference, d = L1 - L2
wire s;
reg sign;
reg i;//an indicator

always @(dividend or divider)
begin
/*save the two operands into temporary registers and manipulate the temps afterwads*/
  tdividend <= dividend;
  tdivider <= divider;
end

always @(tdividend or tdivider)
begin
  error = 0;
  //specical operands
  if (tdivider == 0)
      error = 1;//report error when divider == 0
  
  else if (tdividend == 0)
    begin
      quotient = 0;
      remainder = 0;
    end
  
  //general operands
  else
  begin
      //in signed mode,save the signs and convert the operands to unsigned mode
      if (s == 1)
      begin
      sign = tdividend[31] - tdivider[31];
      if (tdividend[31] == 1)
        begin
        tdividend = tdividend - 1;
        tdividend = ~tdividend;
        end
      if (tdivider[31] == 1)
        begin
        tdivider = tdivider - 1;
        tdivider = ~tdivider;
        end
      end

      //find MSB of dividend
      L1 = 5'd31;
      for (i = 1;L1 >= 0 && i > 0;L1 = L1 - 1)
      begin
      if (tdividend[L1] == 1)
        begin
        i = 0;
	L1 = L1 + 1;
	end
      end
      //find MSB of divider
      L2 = 5'd31;
      for (i = 1;L2 >= 0 && i > 0;L2 = L2 - 1)
      begin
      if (tdivider[L2] == 1)
	begin
	i = 0;	
	L2 = L2 + 1;
	end
      end
	      
      d = L1 - L2;
      remainder = tdividend;
      tdivider = tdivider<<d;
      quotient = 0;
  
      //calculate quotient and remainder in the loop
      for (d = d;d != 5'd31;d = d - 1)
      begin
       if (remainder >= tdivider)
	 begin
	   quotient = {quotient[30:0],1'b0} + 1;
	   remainder = remainder - tdivider;
	   tdivider = tdivider>>1;
	 end
	else
	 begin
	   quotient = {quotient[30:0],1'b0} + 0;
	   remainder = remainder;
	   tdivider = tdivider>>1;
	 end
      end   
    end
    //convert quotient and remainder back to signed mode
    if (s == 1)
    begin
      if (sign == 1)
        begin
        quotient = ~quotient;
        quotient = quotient + 1;
        quotient = {sign,quotient[30:0]};
        end
      remainder = ~remainder;
      remainder = remainder + 1;
    end
end

endmodule

testbench.v
`timescale 1ns/100ps
module tb;
reg [31:0] dividend;
reg [31:0] divider;
reg s;
wire [31:0] quotient;
wire [31:0] remainder;
wire error;

bit32_divider d1(dividend,divider,s,quotient,remainder,error);

initial
begin
  s = 0;dividend = 32'd183;divider = 32'd14;
  #10 dividend = 32'd1000;divider = 32'd100;
  #10 dividend = 32'd1003;divider = 32'd150;
  #10 dividend = 32'd467;divider = 32'd13;
  #10 dividend = 32'd0;divider = 32'd10;
  #10 dividend = 32'd1;divider = 32'd0;
  #10 s = 1;dividend = -32'd892;divider = 32'd67;
  #10 dividend = 32'd60000;divider = -32'd30;
  #10 dividend = -32'd9320634;divider = -32'd1274;
  #10 $stop;
end

initial
begin
  $dumpfile("test.vcd");
  $dumpvars;
end

initial
$monitor($time,"dividend = %d, divider = %d, quotient = %d, remainder = %d, error = %b",dividend,divider,quotient,remainder,error);

endmodule

test.vcd
$date
	Tue Dec 13 22:40:21 2016
$end

$version
	Synopsys VCS version G-2012.09
$end

$timescale
	100ps
$end

$comment Csum: 1 a212b77b198c2d8b $end


$scope module tb $end
$var reg 32 ! dividend [31:0] $end
$var reg 32 " divider [31:0] $end
$var reg 1 # s $end
$var wire 1 $ quotient [31] $end
$var wire 1 % quotient [30] $end
$var wire 1 & quotient [29] $end
$var wire 1 ' quotient [28] $end
$var wire 1 ( quotient [27] $end
$var wire 1 ) quotient [26] $end
$var wire 1 * quotient [25] $end
$var wire 1 + quotient [24] $end
$var wire 1 , quotient [23] $end
$var wire 1 - quotient [22] $end
$var wire 1 . quotient [21] $end
$var wire 1 / quotient [20] $end
$var wire 1 0 quotient [19] $end
$var wire 1 1 quotient [18] $end
$var wire 1 2 quotient [17] $end
$var wire 1 3 quotient [16] $end
$var wire 1 4 quotient [15] $end
$var wire 1 5 quotient [14] $end
$var wire 1 6 quotient [13] $end
$var wire 1 7 quotient [12] $end
$var wire 1 8 quotient [11] $end
$var wire 1 9 quotient [10] $end
$var wire 1 : quotient [9] $end
$var wire 1 ; quotient [8] $end
$var wire 1 < quotient [7] $end
$var wire 1 = quotient [6] $end
$var wire 1 > quotient [5] $end
$var wire 1 ? quotient [4] $end
$var wire 1 @ quotient [3] $end
$var wire 1 A quotient [2] $end
$var wire 1 B quotient [1] $end
$var wire 1 C quotient [0] $end
$var wire 1 D remainder [31] $end
$var wire 1 E remainder [30] $end
$var wire 1 F remainder [29] $end
$var wire 1 G remainder [28] $end
$var wire 1 H remainder [27] $end
$var wire 1 I remainder [26] $end
$var wire 1 J remainder [25] $end
$var wire 1 K remainder [24] $end
$var wire 1 L remainder [23] $end
$var wire 1 M remainder [22] $end
$var wire 1 N remainder [21] $end
$var wire 1 O remainder [20] $end
$var wire 1 P remainder [19] $end
$var wire 1 Q remainder [18] $end
$var wire 1 R remainder [17] $end
$var wire 1 S remainder [16] $end
$var wire 1 T remainder [15] $end
$var wire 1 U remainder [14] $end
$var wire 1 V remainder [13] $end
$var wire 1 W remainder [12] $end
$var wire 1 X remainder [11] $end
$var wire 1 Y remainder [10] $end
$var wire 1 Z remainder [9] $end
$var wire 1 [ remainder [8] $end
$var wire 1 \ remainder [7] $end
$var wire 1 ] remainder [6] $end
$var wire 1 ^ remainder [5] $end
$var wire 1 _ remainder [4] $end
$var wire 1 ` remainder [3] $end
$var wire 1 a remainder [2] $end
$var wire 1 b remainder [1] $end
$var wire 1 c remainder [0] $end
$var wire 1 d error $end

$scope module d1 $end
$var wire 32 ! dividend [31:0] $end
$var wire 32 " divider [31:0] $end
$var wire 1 # s $end
$var reg 32 e quotient [31:0] $end
$var reg 32 f remainder [31:0] $end
$var reg 1 g error $end
$var reg 32 h tdividend [31:0] $end
$var reg 32 i tdivider [31:0] $end
$var reg 5 j L1 [4:0] $end
$var reg 5 k L2 [4:0] $end
$var reg 5 l d [4:0] $end
$var reg 1 m sign $end
$var reg 1 n i $end
$upscope $end

$upscope $end

$enddefinitions $end

#0
$dumpvars
0g
0d
0n
1C
09
08
07
06
05
04
03
02
01
00
0B
0/
0.
0-
0,
0+
0*
0)
0(
0'
0&
1A
0%
0$
1@
0?
0>
0=
0<
0;
0:
1c
0Y
0X
0W
0V
0U
0T
0S
0R
0Q
0P
0b
0O
0N
0M
0L
0K
0J
0I
0H
0G
0F
0a
0E
0D
0`
0_
0^
0]
0\
0[
0Z
0#
xm
b00111 j
b00011 k
b11111 l
b00000000000000000000000010110111 !
b00000000000000000000000000001110 "
b00000000000000000000000000001101 e
b00000000000000000000000000000001 f
b00000000000000000000000010110111 h
b00000000000000000000000000000111 i
$end
#100
b00000000000000000000001111101000 !
b00000000000000000000000001100100 "
b00000000000000000000001111101000 h
b00000000000000000000000001100100 i
b00000000000000000000000000001010 e
0A
1B
0C
b00000000000000000000000000000000 f
0c
b00000000000000000000000000110010 i
b01001 j
b00110 k
#200
b00000000000000000000001111101011 !
b00000000000000000000000010010110 "
b00000000000000000000001111101011 h
b00000000000000000000000010010110 i
b00000000000000000000000000000110 e
0@
1A
b00000000000000000000000001100111 f
1]
1^
1a
1b
1c
b00000000000000000000000001001011 i
b00111 k
#300
b00000000000000000000000111010011 !
b00000000000000000000000000001101 "
b00000000000000000000000111010011 h
b00000000000000000000000000001101 i
b00000000000000000000000000100011 e
1>
0A
1C
b00000000000000000000000000001100 f
0]
0^
1`
0b
0c
b00000000000000000000000000000110 i
b01000 j
b00011 k
#400
b00000000000000000000000000000000 !
b00000000000000000000000000001010 "
b00000000000000000000000000000000 h
b00000000000000000000000000001010 i
b00000000000000000000000000000000 e
0>
0B
0C
b00000000000000000000000000000000 f
0`
0a
#500
b00000000000000000000000000000001 !
b00000000000000000000000000000000 "
b00000000000000000000000000000001 h
b00000000000000000000000000000000 i
1g
1d
#600
1#
b11111111111111111111110010000100 !
b00000000000000000000000001000011 "
b11111111111111111111110010000100 h
b00000000000000000000000001000011 i
0g
0d
b11111111111111111111111111110011 e
1$
1%
1&
1'
1(
1)
1*
1+
1,
1-
1.
1/
10
11
12
13
14
15
16
17
18
19
1:
1;
1<
1=
1>
1?
1B
1C
b11111111111111111111111111101011 f
1D
1E
1F
1G
1H
1I
1J
1K
1L
1M
1N
1O
1P
1Q
1R
1S
1T
1U
1V
1W
1X
1Y
1Z
1[
1\
1]
1^
1`
1b
1c
1m
b00000000000000000000001101111100 h
b00000000000000000000000000100001 i
b01001 j
b00110 k
#700
b00000000000000001110101001100000 !
b11111111111111111111111111100010 "
b00000000000000001110101001100000 h
b11111111111111111111111111100010 i
b11111111111111111111100000110000 e
09
0:
0;
0<
0=
0B
0C
b00000000000000000000000000000000 f
0D
0E
0F
0G
0H
0I
0J
0K
0L
0M
0N
0O
0P
0Q
0R
0S
0T
0U
0V
0W
0X
0Y
0Z
0[
0\
0]
0^
0`
0b
0c
b00000000000000000000000000001111 i
b01111 j
b00100 k
#800
b11111111011100011100011101000110 !
b11111111111111111111101100000110 "
b11111111011100011100011101000110 h
b11111111111111111111101100000110 i
b00000000000000000001110010010100 e
0$
0%
0&
0'
0(
0)
0*
0+
0,
0-
0.
0/
00
01
02
03
04
05
06
19
1<
0>
1A
b11111111111111111111111111001110 f
1D
1E
1F
1G
1H
1I
1J
1K
1L
1M
1N
1O
1P
1Q
1R
1S
1T
1U
1V
1W
1X
1Y
1Z
1[
1\
1]
1`
1a
1b
0m
b00000000100011100011100010111010 h
b00000000000000000000001001111101 i
b10111 j
b01010 k
